didata_cli/__init__.py
didata_cli/cli.py
didata_cli/filterable_response.py
didata_cli/utils.py
didata_cli/commands/__init__.py
didata_cli/commands/cmd_backup.py
didata_cli/commands/cmd_image.py
didata_cli/commands/cmd_location.py
didata_cli/commands/cmd_network.py
didata_cli/commands/cmd_server.py
didata_cli/commands/cmd_tag.py
didata_cli-0.2.4.dist-info/DESCRIPTION.rst
didata_cli-0.2.4.dist-info/METADATA
didata_cli-0.2.4.dist-info/RECORD
didata_cli-0.2.4.dist-info/WHEEL
didata_cli-0.2.4.dist-info/dependency_links.txt
didata_cli-0.2.4.dist-info/entry_points.txt
didata_cli-0.2.4.dist-info/metadata.json
didata_cli-0.2.4.dist-info/top_level.txt
