Metadata-Version: 2.0
Name: didata-cli
Version: 0.2.4
Summary: A CLI to interact with the Dimension Data Cloud API
Home-page: https://www.dimensiondata.com/
Author: Jeff Dunham
Author-email: jeff.dunham@itaas.dimensiondata.com
License: Apache License (2.0)
Platform: UNKNOWN
Classifier: Development Status :: 4 - Beta
Classifier: License :: OSI Approved :: Apache Software License
Classifier: Intended Audience :: End Users/Desktop
Classifier: Programming Language :: Python
Classifier: Programming Language :: Python :: 2.7
Classifier: Programming Language :: Python :: 3.4
Requires-Dist: apache-libcloud (>=1.0.0-pre1)
Requires-Dist: click
Requires-Dist: future
Requires-Dist: tabulate
